igit/__init__.py
igit/cli.py
igit/compression.py
igit/config.py
igit/constants.py
igit/demo.py
igit/diffs.py
igit/encryption.py
igit/hashing.py
igit/igit.py
igit/interval_utils.py
igit/merges.py
igit/models/__init__.py
igit/models/base.py
igit/models/blob.py
igit/models/packet.py
igit/models/reference.py
igit/models/repo.py
igit/models/tree.py
igit/models/user.py
igit/refs.py
igit/remotes.py
igit/repo.py
igit/serializers.py
igit/server.py
igit/storage/__init__.py
igit/storage/common.py
igit/storage/mongo.py
igit/storage/object_store.py
igit/trees/__init__.py
igit/trees/base.py
igit/trees/configs.py
igit/trees/intervals.py
igit/trees/labels.py
igit/utils.py
igit/visualizations.py
interval_git-0.1.1.dist-info/entry_points.txt
interval_git-0.1.1.dist-info/LICENSE
interval_git-0.1.1.dist-info/WHEEL
interval_git-0.1.1.dist-info/METADATA
interval_git-0.1.1.dist-info/RECORD
