Metadata-Version: 2.1
Name: interval-git
Version: 0.1.1
Summary: Top-level package for igit.
Home-page: https://github.com/jmosbacher/igit
License: Apache-2.0
Author: Yossi Mosbacher
Author-email: joe.mosbacher@gmail.com
Requires-Python: >=3.7
Classifier: Development Status :: 2 - Pre-Alpha
Classifier: Intended Audience :: Developers
Classifier: License :: OSI Approved :: Apache Software License
Classifier: Natural Language :: English
Classifier: Programming Language :: Python :: 3
Classifier: Programming Language :: Python :: 3.7
Classifier: Programming Language :: Python :: 3.8
Requires-Dist: Jinja2[server] (>=2.11.3,<3.0.0)
Requires-Dist: aiohttp[server] (>=3.7.4,<4.0.0)
Requires-Dist: click
Requires-Dist: cryptography (>=3.4.7,<4.0.0)
Requires-Dist: dill (>=0.3.3,<0.4.0)
Requires-Dist: fastapi[server] (>=0.63.0,<0.64.0)
Requires-Dist: fsspec (>=2021.4.0,<2022.0.0)
Requires-Dist: hypothesis[numpy,pandas] (>=6.10.1,<7.0.0)
Requires-Dist: intervaltree (>=3.1.0,<4.0.0)
Requires-Dist: msgpack (>=1.0.2,<2.0.0)
Requires-Dist: msgpack-numpy (>=0.4.7,<0.5.0)
Requires-Dist: pydantic (>=1.8.1,<2.0.0)
Requires-Dist: pymongo (>=3.11.3,<4.0.0)
Requires-Dist: requests[server] (>=2.25.1,<3.0.0)
Requires-Dist: treelib (>=1.6.1,<2.0.0)
Requires-Dist: zict (>=2.0.0,<3.0.0)
